charts_pythondouble/__init__.py
charts_pythondouble/bar.py
charts_pythondouble/charts.py
charts_pythondouble/line.py
charts_pythondouble/main.py
charts_pythondouble-0.0.6.dist-info/LICENSE
charts_pythondouble-0.0.6.dist-info/METADATA
charts_pythondouble-0.0.6.dist-info/WHEEL
charts_pythondouble-0.0.6.dist-info/top_level.txt
charts_pythondouble-0.0.6.dist-info/RECORD
