Metadata-Version: 2.1
Name: charts-pythondouble
Version: 0.0.6
Summary: UNKNOWN
Home-page: https://github.com
Author: jack.253png
Author-email: guoxiuchen20170402@163.com
License: UNKNOWN
Platform: UNKNOWN
Requires-Dist: pyecharts
